objectstate/__init__.py
objectstate/collection_containers.py
objectstate/config.py
objectstate/context_manager.py
objectstate/dual_axis_resolver.py
objectstate/global_config.py
objectstate/lazy_factory.py
objectstate/live_context_resolver.py
objectstate/object_state.py
objectstate/parametric_axes.py
objectstate/placeholder.py
objectstate/reified_generics.py
objectstate/snapshot_model.py
objectstate/token_cache.py
objectstate/docs/configuration_framework.rst
objectstate/docs/context_system.rst
objectstate/docs/object_state_lifecycle.rst
objectstate-1.0.9.dist-info/METADATA
objectstate-1.0.9.dist-info/WHEEL
objectstate-1.0.9.dist-info/licenses/LICENSE
objectstate-1.0.9.dist-info/RECORD
