Metadata-Version: 2.4
Name: objectstate
Version: 1.0.9
Summary: Generic lazy dataclass configuration framework with dual-axis inheritance and contextvars-based resolution
Project-URL: Homepage, https://github.com/OpenHCSDev/objectstate
Project-URL: Documentation, https://objectstate.readthedocs.io
Project-URL: Repository, https://github.com/OpenHCSDev/objectstate
Project-URL: Issues, https://github.com/OpenHCSDev/objectstate/issues
Author-email: Tristan Simas <tristan.simas@mail.mcgill.ca>
License: MIT
License-File: LICENSE
Keywords: configuration,contextvars,dataclass,hierarchical,inheritance,lazy
Classifier: Development Status :: 4 - Beta
Classifier: Intended Audience :: Developers
Classifier: License :: OSI Approved :: MIT License
Classifier: Programming Language :: Python :: 3
Classifier: Programming Language :: Python :: 3.11
Classifier: Programming Language :: Python :: 3.12
Classifier: Programming Language :: Python :: 3.13
Classifier: Topic :: Software Development :: Libraries :: Python Modules
Classifier: Topic :: Utilities
Requires-Python: >=3.11
Requires-Dist: python-introspect>=0.1.0
Provides-Extra: dev
Requires-Dist: black>=23.0; extra == 'dev'
Requires-Dist: mypy>=1.0; extra == 'dev'
Requires-Dist: pytest-cov>=4.0; extra == 'dev'
Requires-Dist: pytest>=7.0; extra == 'dev'
Requires-Dist: ruff>=0.1.0; extra == 'dev'
Provides-Extra: docs
Requires-Dist: sphinx-autodoc-typehints>=1.25; extra == 'docs'
Requires-Dist: sphinx-rtd-theme>=2.0; extra == 'docs'
Requires-Dist: sphinx>=7.0; extra == 'docs'
